tests/__init__.py
tests/test_bubble.py
tests/test_cancel.py
tests/test_executor.py
tests/test_general.py
tests/test_join.py
tests/test_master.py
tests/test_misuse.py
tests/test_nested.py
tests/test_timeout.py
traio/__init__.py
traio/__version__.py
traio/nursery.py
traio/scope.py
traio/task.py
traio-0.5.2.dist-info/LICENSE
traio-0.5.2.dist-info/METADATA
traio-0.5.2.dist-info/WHEEL
traio-0.5.2.dist-info/top_level.txt
traio-0.5.2.dist-info/RECORD
