Metadata-Version: 2.1
Name: traio
Version: 0.5.2
Summary: A simple asyncio wrapper attempting to look like Trio
Home-page: https://github.com/RouquinBlanc/traio/
Author: Jonathan Martin
Author-email: therouquinblanc@gmail.com
License: MIT
Keywords: asyncio,nursery,trio,even loop
Platform: UNKNOWN
Classifier: Development Status :: 4 - Beta
Classifier: Operating System :: OS Independent
Classifier: Intended Audience :: Developers
Classifier: Programming Language :: Python :: 3
Classifier: Programming Language :: Python :: 3.5
Classifier: Programming Language :: Python :: 3.6
Classifier: Programming Language :: Python :: 3.7
Requires-Dist: aiocontextvars (~=0.2)
Requires-Dist: typing; python_version < "3.6"
